odoo/addons/multisearch_field/README.rst
odoo/addons/multisearch_field/__init__.py
odoo/addons/multisearch_field/__manifest__.py
odoo/addons/multisearch_field/data/multi_search_data.xml
odoo/addons/multisearch_field/i18n/multisearch_field.pot
odoo/addons/multisearch_field/models/__init__.py
odoo/addons/multisearch_field/models/base.py
odoo/addons/multisearch_field/readme/CONFIGURE.rst
odoo/addons/multisearch_field/readme/CONTRIBUTORS.rst
odoo/addons/multisearch_field/readme/DESCRIPTION.rst
odoo/addons/multisearch_field/readme/USAGE.rst
odoo/addons/multisearch_field/static/description/icon.png
odoo/addons/multisearch_field/static/description/index.html
odoo/addons/multisearch_field/static/description/img/After_multi_search.png
odoo/addons/multisearch_field/static/description/img/Before_multi_search.png
odoo/addons/multisearch_field/tests/__init__.py
odoo/addons/multisearch_field/tests/test_multi_search.py
odoo_addon_multisearch_field-16.0.1.0.0.2.dist-info/METADATA
odoo_addon_multisearch_field-16.0.1.0.0.2.dist-info/WHEEL
odoo_addon_multisearch_field-16.0.1.0.0.2.dist-info/top_level.txt
odoo_addon_multisearch_field-16.0.1.0.0.2.dist-info/RECORD
