Metadata-Version: 2.1
Name: odoo-addon-multisearch_field
Version: 16.0.1.0.0.2
Summary: add modification on search to search multi_value with separator
Home-page: https://github.com/OCA/server-ux
Author: Akretion, Odoo Community Association (OCA)
Author-email: support@odoo-community.org
License: AGPL-3
Classifier: Programming Language :: Python
Classifier: Framework :: Odoo
Classifier: Framework :: Odoo :: 16.0
Classifier: License :: OSI Approved :: GNU Affero General Public License v3
Requires-Python: >=3.10
Requires-Dist: odoo<16.1dev,>=16.0a
